[{
		"nome":	"usuario3",
		"idade":	1
	}, {
		"nome":	"usuario8",
		"idade":	15
	}, {
		"nome":	"usuario19",
		"idade":	11
	}, {
		"nome":	"usuario22",
		"idade":	2
	}, {
		"nome":	"usuario26",
		"idade":	17
	}, {
		"nome":	"usuario32",
		"idade":	3
	}, {
		"nome":	"usuario39",
		"idade":	6
	}, {
		"nome":	"usuario49",
		"idade":	2
	}, {
		"nome":	"usuario50",
		"idade":	13
	}, {
		"nome":	"usuario59",
		"idade":	5
	}, {
		"nome":	"usuario60",
		"idade":	6
	}, {
		"nome":	"usuario62",
		"idade":	15
	}, {
		"nome":	"usuario64",
		"idade":	13
	}, {
		"nome":	"usuario69",
		"idade":	12
	}, {
		"nome":	"usuario71",
		"idade":	6
	}, {
		"nome":	"usuario74",
		"idade":	7
	}, {
		"nome":	"usuario79",
		"idade":	15
	}, {
		"nome":	"usuario80",
		"idade":	4
	}, {
		"nome":	"usuario87",
		"idade":	17
	}, {
		"nome":	"usuario89",
		"idade":	11
	}, {
		"nome":	"usuario91",
		"idade":	3
	}, {
		"nome":	"usuario94",
		"idade":	0
	}, {
		"nome":	"usuario95",
		"idade":	1
	}, {
		"nome":	"usuario96",
		"idade":	14
	}]